ascend_connectors/__init__.py
ascend_connectors-0.1.1.dist-info/METADATA
ascend_connectors-0.1.1.dist-info/WHEEL
ascend_connectors-0.1.1.dist-info/entry_points.txt
ascend_connectors-0.1.1.dist-info/RECORD
