Metadata-Version: 2.4
Name: ascend-connectors
Version: 0.1.1
Summary: Ascend Python Connector plugins
Author-email: Ascend developers <hello@ascend.io>
Requires-Python: >=3.10
Provides-Extra: salesforce
Requires-Dist: simple-salesforce>=1.12.6; extra == 'salesforce'
